edam_ontology/EDAM.tsv
edam_ontology/__init__.py
edam_ontology/streams.py
edam_ontology-1.25.2.dev0.dist-info/LICENSE
edam_ontology-1.25.2.dev0.dist-info/METADATA
edam_ontology-1.25.2.dev0.dist-info/WHEEL
edam_ontology-1.25.2.dev0.dist-info/entry_points.txt
edam_ontology-1.25.2.dev0.dist-info/top_level.txt
edam_ontology-1.25.2.dev0.dist-info/RECORD
