Metadata-Version: 2.1
Name: edam-ontology
Version: 1.25.2.dev0
Summary: Versioned, Python packaged EDAM ontology (http://edamontology.org/) data.
Home-page: https://github.com/edamontology/edam-ontology.py
Author: edamontology
Author-email: jmchilton@gmail.com
License: MIT
Keywords: EDAM
Platform: UNKNOWN
Classifier: Development Status :: 5 - Production/Stable
Classifier: Intended Audience :: Developers
Classifier: Environment :: Console
Classifier: License :: OSI Approved :: MIT License
Classifier: Operating System :: POSIX
Classifier: Topic :: Software Development
Classifier: Topic :: Software Development :: Code Generators
Classifier: Topic :: Software Development :: Testing
Classifier: Natural Language :: English
Classifier: Programming Language :: Python :: 3
Classifier: Programming Language :: Python :: 3.5
Classifier: Programming Language :: Python :: 3.6
Classifier: Programming Language :: Python :: 3.7
Classifier: Programming Language :: Python :: 3.8
Classifier: Programming Language :: Python :: 3.9
License-File: LICENSE
